h2o_mlops/VERSION
h2o_mlops/__init__.py
h2o_mlops/_artifacts.py
h2o_mlops/_batch_scoring_jobs.py
h2o_mlops/_configs.py
h2o_mlops/_connectors.py
h2o_mlops/_core.py
h2o_mlops/_datasets.py
h2o_mlops/_deployments.py
h2o_mlops/_endpoints.py
h2o_mlops/_events.py
h2o_mlops/_experiments.py
h2o_mlops/_models.py
h2o_mlops/_runtimes.py
h2o_mlops/_users.py
h2o_mlops/_utils.py
h2o_mlops/_version.py
h2o_mlops/_workspaces.py
h2o_mlops/_autogen/__init__.py
h2o_mlops/_autogen/_h2o_mlops_client/__init__.py
h2o_mlops/_autogen/_h2o_mlops_client/batch/__init__.py
h2o_mlops/_autogen/_h2o_mlops_client/batch/api_client.py
h2o_mlops/_autogen/_h2o_mlops_client/batch/configuration.py
h2o_mlops/_autogen/_h2o_mlops_client/batch/exceptions.py
h2o_mlops/_autogen/_h2o_mlops_client/batch/rest.py
h2o_mlops/_autogen/_h2o_mlops_client/batch/api/__init__.py
h2o_mlops/_autogen/_h2o_mlops_client/batch/api/job_service_api.py
h2o_mlops/_autogen/_h2o_mlops_client/batch/api/sink_spec_service_api.py
h2o_mlops/_autogen/_h2o_mlops_client/batch/api/source_spec_service_api.py
h2o_mlops/_autogen/_h2o_mlops_client/batch/models/__init__.py
h2o_mlops/_autogen/_h2o_mlops_client/batch/models/job_state.py
h2o_mlops/_autogen/_h2o_mlops_client/batch/models/model_request_parameters_shapley_type.py
h2o_mlops/_autogen/_h2o_mlops_client/batch/models/protobuf_any.py
h2o_mlops/_autogen/_h2o_mlops_client/batch/models/rpc_status.py
h2o_mlops/_autogen/_h2o_mlops_client/batch/models/stream_result_of_v1_job_output_response.py
h2o_mlops/_autogen/_h2o_mlops_client/batch/models/v1_batch_parameters.py
h2o_mlops/_autogen/_h2o_mlops_client/batch/models/v1_cancel_job_response.py
h2o_mlops/_autogen/_h2o_mlops_client/batch/models/v1_completion_stats.py
h2o_mlops/_autogen/_h2o_mlops_client/batch/models/v1_create_job_response.py
h2o_mlops/_autogen/_h2o_mlops_client/batch/models/v1_deployment_composition.py
h2o_mlops/_autogen/_h2o_mlops_client/batch/models/v1_get_job_response.py
h2o_mlops-1.4.8.dist-info/licenses/LICENSE
h2o_mlops-1.4.8.dist-info/METADATA
h2o_mlops-1.4.8.dist-info/WHEEL
h2o_mlops-1.4.8.dist-info/top_level.txt
h2o_mlops-1.4.8.dist-info/RECORD
