Metadata-Version: 2.4
Name: h2o_mlops
Version: 1.4.8
Summary: Python client for H2O MLOps.
Author-email: "H2O.ai" <support@h2o.ai>
License: Apache v2
Project-URL: Documentation, https://docs.h2o.ai/mlops/py-client/overview
Project-URL: Changelog, https://docs.h2o.ai/mlops/release-notes
Keywords: h2o,mlops
Classifier: Development Status :: 3 - Alpha
Classifier: Programming Language :: Python :: 3.9
Requires-Python: >=3.9
License-File: LICENSE
Requires-Dist: certifi>=2024.7.4
Requires-Dist: h2o-authn>=2.0.1
Requires-Dist: h2o-cloud-discovery>=2.0.0
Requires-Dist: httpx>=0.27.0
Requires-Dist: tabulate>=0.9.0
Requires-Dist: urllib3>=1.26.19
Requires-Dist: yarl>=1.9.4
Requires-Dist: backports.strenum>=1.3.1; python_version < "3.11"
Requires-Dist: markdown>=3.8
Requires-Dist: python-dateutil>=2.9.0.post0
Requires-Dist: six>=1.16.0
Provides-Extra: pyspark
Requires-Dist: pyspark>=3.5.0; python_version >= "3.10" and extra == "pyspark"
Requires-Dist: pyarrow>=19.0.0; python_version >= "3.10" and extra == "pyspark"
Requires-Dist: numpy>=2.2.0; python_version >= "3.10" and extra == "pyspark"
Requires-Dist: pandas>=2.2.0; python_version >= "3.10" and extra == "pyspark"
Requires-Dist: pyspark>=3.5.0; python_version == "3.9" and extra == "pyspark"
Requires-Dist: pyarrow>=19.0.0; python_version == "3.9" and extra == "pyspark"
Requires-Dist: numpy<=2.0.2; python_version == "3.9" and extra == "pyspark"
Requires-Dist: pandas<=2.2.3; python_version == "3.9" and extra == "pyspark"
Dynamic: license-file
